django_obm/__init__.py
django_obm/blockchain/__init__.py
django_obm/blockchain/admin.py
django_obm/blockchain/apps.py
django_obm/blockchain/exceptions.py
django_obm/blockchain/models.py
django_obm/blockchain/connectors/__init__.py
django_obm/blockchain/connectors/_base.py
django_obm/blockchain/connectors/_exceptions.py
django_obm/blockchain/connectors/_registry.py
django_obm/blockchain/connectors/_utils.py
django_obm/blockchain/connectors/btc.py
django_obm/blockchain/management/__init__.py
django_obm/blockchain/management/commands/__init__.py
django_obm/blockchain/management/commands/init_nodes.py
django_obm/blockchain/management/commands/run_receipts_processing.py
django_obm/blockchain/migrations/0001_initial.py
django_obm/blockchain/migrations/__init__.py
django_obm/rest/__init__.py
django_obm/rest/apps.py
django_obm/rest/pagination.py
django_obm/rest/serializers.py
django_obm/rest/urls.py
django_obm/rest/views.py
django_obm/rest/migrations/__init__.py
django_obm-0.2.0.dist-info/AUTHORS
django_obm-0.2.0.dist-info/LICENSE
django_obm-0.2.0.dist-info/METADATA
django_obm-0.2.0.dist-info/WHEEL
django_obm-0.2.0.dist-info/top_level.txt
django_obm-0.2.0.dist-info/RECORD
