Metadata-Version: 2.1
Name: django-obm
Version: 0.2.0
Summary: A Django app for receiving payments in cryptocurrencies.
Home-page: https://github.com/HelloCreepy/django-obm
Author: Alexander Polishchuk
Author-email: apolishchuk52@gmail.com
License: GNU Lesser General Public License v3 or later (LGPLv3+)
Platform: UNKNOWN
Classifier: Environment :: Web Environment
Classifier: Framework :: Django
Classifier: Framework :: Django :: 2.2
Classifier: Framework :: Django :: 3.0
Classifier: Intended Audience :: Developers
Classifier: License :: OSI Approved :: GNU Lesser General Public License v3 or later (LGPLv3+)
Classifier: Operating System :: OS Independent
Classifier: Programming Language :: Python
Classifier: Programming Language :: Python :: 3.7
Classifier: Programming Language :: Python :: 3.8
Classifier: Programming Language :: Python :: 3 :: Only
Classifier: Topic :: Internet :: WWW/HTTP
Classifier: Topic :: Internet :: WWW/HTTP :: Dynamic Content
Requires-Dist: Django (<4,>=2.2)
Requires-Dist: requests (<3,>=2)
Requires-Dist: djangorestframework (<4,>=3)
Provides-Extra: dev
Requires-Dist: sphinx (<3,>=2.4) ; extra == 'dev'
Requires-Dist: sphinx-rtd-theme ; extra == 'dev'
Requires-Dist: pytest ; extra == 'dev'
Requires-Dist: pytest-django ; extra == 'dev'
Requires-Dist: pylint ; extra == 'dev'
Requires-Dist: pylint-django ; extra == 'dev'
Requires-Dist: mypy ; extra == 'dev'
Requires-Dist: rope ; extra == 'dev'
